{"source":"INTERGROWTH-21st International Postnatal Growth Standards for Preterm Infants (intergrowth21.com) — official z-score tables, PMA 27–64 weeks; Villar et al. Lancet Glob Health 2015;3:e681-91. L/S fit per row to the published z=-3..+3 values; M is the published median (z=0).","standard":"intergrowth","sex":"feminino","indicator":"head-circumference-for-age","ageUnit":"months","ageMin":-2.99,"ageMax":5.52,"version":"intergrowth-21st-preterm-postnatal-2015","rows":[{"ageMonths":-2.99,"L":1.04,"M":24,"S":0.07216},{"ageMonths":-2.76,"L":1,"M":25.1,"S":0.06374},{"ageMonths":-2.53,"L":1.1725,"M":26.2,"S":0.05638},{"ageMonths":-2.3,"L":0.797,"M":27.1,"S":0.05088},{"ageMonths":-2.07,"L":1.226,"M":28.1,"S":0.04698},{"ageMonths":-1.84,"L":1,"M":28.9,"S":0.04276},{"ageMonths":-1.61,"L":0.911,"M":29.7,"S":0.03944},{"ageMonths":-1.38,"L":1.1205,"M":30.5,"S":0.03712},{"ageMonths":-1.15,"L":1,"M":31.2,"S":0.03526},{"ageMonths":-0.92,"L":1.294,"M":31.9,"S":0.0329},{"ageMonths":-0.69,"L":1,"M":32.5,"S":0.03186},{"ageMonths":-0.46,"L":0.702,"M":33.1,"S":0.03054},{"ageMonths":-0.23,"L":1,"M":33.7,"S":0.02968},{"ageMonths":0,"L":0.53,"M":34.2,"S":0.02872},{"ageMonths":0.23,"L":1.51,"M":34.8,"S":0.0281},{"ageMonths":0.46,"L":1.41,"M":35.3,"S":0.0277},{"ageMonths":0.69,"L":0.845,"M":35.7,"S":0.02722},{"ageMonths":0.92,"L":1.79,"M":36.2,"S":0.02698},{"ageMonths":1.15,"L":0.996,"M":36.6,"S":0.02674},{"ageMonths":1.38,"L":0.491,"M":37,"S":0.02654},{"ageMonths":1.61,"L":1,"M":37.4,"S":0.02674},{"ageMonths":1.84,"L":1,"M":37.8,"S":0.02646},{"ageMonths":2.07,"L":0.41,"M":38.1,"S":0.0268},{"ageMonths":2.3,"L":1,"M":38.5,"S":0.02598},{"ageMonths":2.53,"L":0.4705,"M":38.8,"S":0.02632},{"ageMonths":2.76,"L":1.59,"M":39.2,"S":0.02602},{"ageMonths":2.99,"L":1.59,"M":39.5,"S":0.02638},{"ageMonths":3.22,"L":1.59,"M":39.8,"S":0.02652},{"ageMonths":3.45,"L":0.821,"M":40,"S":0.0267},{"ageMonths":3.68,"L":0.51,"M":40.3,"S":0.02686},{"ageMonths":3.91,"L":1,"M":40.6,"S":0.0271},{"ageMonths":4.14,"L":0.41,"M":40.8,"S":0.02748},{"ageMonths":4.37,"L":1.004,"M":41.1,"S":0.02728},{"ageMonths":4.6,"L":0.8355,"M":41.3,"S":0.02742},{"ageMonths":4.83,"L":1.31,"M":41.6,"S":0.02764},{"ageMonths":5.06,"L":1,"M":41.8,"S":0.02786},{"ageMonths":5.29,"L":0.8745,"M":42,"S":0.0279},{"ageMonths":5.52,"L":1,"M":42.2,"S":0.02844}]}
